[
   {
    "image": "app_images/photo_editor_pro.png",
    "title": "PhotoEdit Pro",
    "companyName": "PixelCraft Studios",
    "id": 404,
    "appName": "LensSpark",
    "description": "Advanced photo editing with professional filters and tools.",
    "size": 95,
    "reviews": 55000,
    "ratingAvg": 4.6,
    "downloads": "8M",
    "ratings": [
      { "name": "1 star", "count": 3000 },
      { "name": "2 star", "count": 5000 },
      { "name": "3 star", "count": 10000 },
      { "name": "4 star", "count": 17000 },
      { "name": "5 star", "count": 20000 }
    ],
    "downloadCategory": "Highly Popular",
    "downloadsInMillions": 3.1
  },
  {
    "image": "app_images/fit_track_pro.png",
    "title": "FitTrack Pro",
    "companyName": "Wellness Corp",
    "id": 101,
    "appName": "HealthyLife",
    "description": "Daily fitness and workout tracker with GPS integration.",
    "size": 45,
    "reviews": 120000,
    "ratingAvg": 4.8,
    "downloads": "15M",
    "ratings": [
      { "name": "1 star", "count": 1000 },
      { "name": "2 star", "count": 1500 },
      { "name": "3 star", "count": 5000 },
      { "name": "4 star", "count": 32000 },
      { "name": "5 star", "count": 80500 }
    ],
    "downloadCategory": "Top Tier",
    "downloadsInMillions": 15.0
  },
  {
    "image": "app_images/astrolens.png",
    "title": "AstroLens",
    "companyName": "SkyView Devs",
    "id": 202,
    "appName": "StarGazer",
    "description": "Explore constellations, planets, and space phenomena in real-time.",
    "size": 112,
    "reviews": 34000,
    "ratingAvg": 4.5,
    "downloads": "5M",
    "ratings": [
      { "name": "1 star", "count": 2500 },
      { "name": "2 star", "count": 3000 },
      { "name": "3 star", "count": 6000 },
      { "name": "4 star", "count": 9500 },
      { "name": "5 star", "count": 13000 }
    ],
    "downloadCategory": "Popular",
    "downloadsInMillions": 5.0
  },
  {
    "image": "app_images/notestream.png",
    "title": "NoteStream",
    "companyName": "WriteNow Tech",
    "id": 303,
    "appName": "QuickNotes",
    "description": "Cloud-synced, minimalist, and powerful note-taking application.",
    "size": 22,
    "reviews": 500000,
    "ratingAvg": 4.9,
    "downloads": "50M",
    "ratings": [
      { "name": "1 star", "count": 5000 },
      { "name": "2 star", "count": 5000 },
      { "name": "3 star", "count": 10000 },
      { "name": "4 star", "count": 70000 },
      { "name": "5 star", "count": 410000 }
    ],
    "downloadCategory": "Mega Hit",
    "downloadsInMillions": 50.0
  },
  {
    "image": "app_images/gamehub_x.png",
    "title": "GameHub X",
    "companyName": "PixelPlay Inc",
    "id": 505,
    "appName": "Nexus Arcade",
    "description": "A collection of classic and indie games with monthly updates.",
    "size": 210,
    "reviews": 95000,
    "ratingAvg": 4.2,
    "downloads": "11M",
    "ratings": [
      { "name": "1 star", "count": 8000 },
      { "name": "2 star", "count": 9000 },
      { "name": "3 star", "count": 15000 },
      { "name": "4 star", "count": 23000 },
      { "name": "5 star", "count": 40000 }
    ],
    "downloadCategory": "High Volume",
    "downloadsInMillions": 11.0
  },
  {
    "image": "app_images/recipe_flow.png",
    "title": "RecipeFlow",
    "companyName": "Culinary Apps",
    "id": 606,
    "appName": "TasteBuds",
    "description": "Step-by-step cooking guides, meal plans, and personalized recipe recommendations.",
    "size": 78,
    "reviews": 62000,
    "ratingAvg": 4.7,
    "downloads": "7M",
    "ratings": [
      { "name": "1 star", "count": 1500 },
      { "name": "2 star", "count": 2500 },
      { "name": "3 star", "count": 5000 },
      { "name": "4 star", "count": 18000 },
      { "name": "5 star", "count": 35000 }
    ],
    "downloadCategory": "Standard",
    "downloadsInMillions": 7.0
  },
  {
    "image": "app_images/money_wise.png",
    "title": "MoneyWise",
    "companyName": "FinanceFast",
    "id": 707,
    "appName": "BudgetPro",
    "description": "Intuitive personal finance and expense tracking tool with automated categorization.",
    "size": 35,
    "reviews": 180000,
    "ratingAvg": 4.6,
    "downloads": "20M",
    "ratings": [
      { "name": "1 star", "count": 5000 },
      { "name": "2 star", "count": 6000 },
      { "name": "3 star", "count": 19000 },
      { "name": "4 star", "count": 45000 },
      { "name": "5 star", "count": 105000 }
    ],
    "downloadCategory": "Very Popular",
    "downloadsInMillions": 20.0
  },
  {
    "image": "app_images/vox_talk.png",
    "title": "VoxTalk",
    "companyName": "Global Comms",
    "id": 808,
    "appName": "LanguagePro",
    "description": "Interactive language learning with native speaker exercises and conversation practice.",
    "size": 88,
    "reviews": 250000,
    "ratingAvg": 4.4,
    "downloads": "30M",
    "ratings": [
      { "name": "1 star", "count": 10000 },
      { "name": "2 star", "count": 15000 },
      { "name": "3 star", "count": 40000 },
      { "name": "4 star", "count": 75000 },
      { "name": "5 star", "count": 110000 }
    ],
    "downloadCategory": "High Volume",
    "downloadsInMillions": 30.0
  },
  {
    "image": "app_images/draw_pad_ai.png",
    "title": "DrawPad AI",
    "companyName": "Creative Labs",
    "id": 909,
    "appName": "ArtStudio",
    "description": "AI-powered digital drawing and painting application with advanced brush tools.",
    "size": 65,
    "reviews": 80000,
    "ratingAvg": 4.3,
    "downloads": "9M",
    "ratings": [
      { "name": "1 star", "count": 6000 },
      { "name": "2 star", "count": 8000 },
      { "name": "3 star", "count": 12000 },
      { "name": "4 star", "count": 22000 },
      { "name": "5 star", "count": 32000 }
    ],
    "downloadCategory": "Niche Hit",
    "downloadsInMillions": 9.0
  },
  {
    "image": "app_images/code_mentor.png",
    "title": "CodeMentor",
    "companyName": "DevTools King",
    "id": 111,
    "appName": "LearnCode",
    "description": "Interactive coding tutorials and quizzes for various programming languages.",
    "size": 40,
    "reviews": 30000,
    "ratingAvg": 4.7,
    "downloads": "4M",
    "ratings": [
      { "name": "1 star", "count": 500 },
      { "name": "2 star", "count": 1000 },
      { "name": "3 star", "count": 2500 },
      { "name": "4 star", "count": 9000 },
      { "name": "5 star", "count": 17000 }
    ],
    "downloadCategory": "Starter",
    "downloadsInMillions": 4.0
  },
  {
    "image": "app_images/sleep_well.png",
    "title": "SleepWell",
    "companyName": "Restful Apps",
    "id": 222,
    "appName": "DreamEasy",
    "description": "White noise, sleep stories, and soundscapes for better relaxation and sleep.",
    "size": 30,
    "reviews": 150000,
    "ratingAvg": 4.8,
    "downloads": "18M",
    "ratings": [
      { "name": "1 star", "count": 1500 },
      { "name": "2 star", "count": 2500 },
      { "name": "3 star", "count": 5000 },
      { "name": "4 star", "count": 35000 },
      { "name": "5 star", "count": 106000 }
    ],
    "downloadCategory": "Highly Popular",
    "downloadsInMillions": 18.0
  },
  {
    "image": "app_images/zen_flow.png",
    "title": "ZenFlow",
    "companyName": "Mindful Studio",
    "id": 444,
    "appName": "MeditationNow",
    "description": "Guided meditations and breathing exercises for stress and anxiety reduction.",
    "size": 55,
    "reviews": 110000,
    "ratingAvg": 4.9,
    "downloads": "12M",
    "ratings": [
      { "name": "1 star", "count": 500 },
      { "name": "2 star", "count": 1000 },
      { "name": "3 star", "count": 2500 },
      { "name": "4 star", "count": 16000 },
      { "name": "5 star", "count": 90000 }
    ],
    "downloadCategory": "Top Tier",
    "downloadsInMillions": 12.0
  }
]